ciopath/LICENSE
ciopath/README.md
ciopath/VERSION
ciopath/__init__.py
ciopath/gpath.py
ciopath/gpath_list.py
tests/__init__.py
tests/test_gpath.py
tests/test_gpath_list.py
tests/mocks/__init__.py
tests/mocks/glob.py
ciopath-1.1.2.dist-info/LICENSE
ciopath-1.1.2.dist-info/METADATA
ciopath-1.1.2.dist-info/WHEEL
ciopath-1.1.2.dist-info/top_level.txt
ciopath-1.1.2.dist-info/RECORD
