Metadata-Version: 2.1
Name: ciopath
Version: 1.1.2
Summary: Object-oriented platform-transparent path manipulations.
Home-page: https://github.com/ConductorTechnologies/sequence
Author: conductor
Author-email: info@conductortech.com
Classifier: Operating System :: OS Independent
Classifier: Programming Language :: Python
License-File: LICENSE
Requires-Dist: future (>=0.18.2)
